[
  {
    "title": "Przesłony wewnętrzne",
    "items": [
      { "label": "Rolety materiałowe" },
      { "label": "Rolety dzień-noc" },
      { "label": "Plisy" },
      { "label": "Zasłony rzymskie" },
      { "label": "Zasłony materiałowe" },
      { "label": "Żaluzje aluminiowe" },
      { "label": "Żaluzje drewniane i bambusowe" },
      { "label": "Żaluzje pionowe" }
    ]
  },
  {
    "title": "Przesłony zewnętrzne",
    "items": [
      { "label": "Rolety zewnętrzne" },
      { "label": "Rolety typu screen" },
      { "label": "Żaluzje zewnętrzne" },
      { "label": "Moskitiery" }
    ]
  },
  {
    "title": "Inne",
    "items": [{ "label": "Automatyka do rolet i bram" }]
  }
]
